{
  "CUGAL_CPU.sim.max": {
    "steps": [
      0,
      1,
      2,
      3,
      4,
      5
    ],
    "timestamps": [
      "2024-06-03T20:38:20.272792",
      "2024-06-03T20:38:31.353698",
      "2024-06-03T20:38:43.294786",
      "2024-06-03T20:38:53.709535",
      "2024-06-03T20:39:05.977705",
      "2024-06-03T20:39:18.173752"
    ],
    "values": [
      1.0,
      1.0,
      1.0,
      1.0,
      1.0,
      1.0
    ]
  },
  "CUGAL_CPU.sim.min": {
    "steps": [
      0,
      1,
      2,
      3,
      4,
      5
    ],
    "timestamps": [
      "2024-06-03T20:38:20.272864",
      "2024-06-03T20:38:31.353760",
      "2024-06-03T20:38:43.294854",
      "2024-06-03T20:38:53.709593",
      "2024-06-03T20:39:05.977775",
      "2024-06-03T20:39:18.173809"
    ],
    "values": [
      0.0,
      0.0,
      0.0,
      0.0,
      0.0,
      0.0
    ]
  },
  "CUGAL_CPU.sim.size": {
    "steps": [
      0,
      1,
      2,
      3,
      4,
      5
    ],
    "timestamps": [
      "2024-06-03T20:38:20.272661",
      "2024-06-03T20:38:31.353567",
      "2024-06-03T20:38:43.294638",
      "2024-06-03T20:38:53.709397",
      "2024-06-03T20:39:05.977580",
      "2024-06-03T20:39:18.173629"
    ],
    "values": [
      143641,
      143641,
      143641,
      143641,
      143641,
      143641
    ]
  },
  "CUGAL_FW_010.sim.max": {
    "steps": [
      0,
      1,
      2,
      3,
      4,
      5
    ],
    "timestamps": [
      "2024-06-03T20:38:22.257804",
      "2024-06-03T20:38:33.017283",
      "2024-06-03T20:38:44.584952",
      "2024-06-03T20:38:55.733309",
      "2024-06-03T20:39:07.905228",
      "2024-06-03T20:39:19.709650"
    ],
    "values": [
      1.0,
      1.0,
      1.0,
      1.0,
      1.0,
      1.0
    ]
  },
  "CUGAL_FW_010.sim.min": {
    "steps": [
      0,
      1,
      2,
      3,
      4,
      5
    ],
    "timestamps": [
      "2024-06-03T20:38:22.257859",
      "2024-06-03T20:38:33.017334",
      "2024-06-03T20:38:44.585000",
      "2024-06-03T20:38:55.733355",
      "2024-06-03T20:39:07.905283",
      "2024-06-03T20:39:19.709697"
    ],
    "values": [
      0.0,
      0.0,
      0.0,
      0.0,
      0.0,
      0.0
    ]
  },
  "CUGAL_FW_010.sim.size": {
    "steps": [
      0,
      1,
      2,
      3,
      4,
      5
    ],
    "timestamps": [
      "2024-06-03T20:38:22.257715",
      "2024-06-03T20:38:33.017203",
      "2024-06-03T20:38:44.584883",
      "2024-06-03T20:38:55.733244",
      "2024-06-03T20:39:07.905138",
      "2024-06-03T20:39:19.709585"
    ],
    "values": [
      143641,
      143641,
      143641,
      143641,
      143641,
      143641
    ]
  },
  "CUGAL_FW_020.sim.max": {
    "steps": [
      0,
      1,
      2,
      3,
      4,
      5
    ],
    "timestamps": [
      "2024-06-03T20:38:22.747270",
      "2024-06-03T20:38:33.789740",
      "2024-06-03T20:38:45.052215",
      "2024-06-03T20:38:56.458020",
      "2024-06-03T20:39:08.747181",
      "2024-06-03T20:39:20.324162"
    ],
    "values": [
      1.0,
      1.0,
      1.0,
      1.0,
      1.0,
      1.0
    ]
  },
  "CUGAL_FW_020.sim.min": {
    "steps": [
      0,
      1,
      2,
      3,
      4,
      5
    ],
    "timestamps": [
      "2024-06-03T20:38:22.747324",
      "2024-06-03T20:38:33.789786",
      "2024-06-03T20:38:45.052265",
      "2024-06-03T20:38:56.458076",
      "2024-06-03T20:39:08.747243",
      "2024-06-03T20:39:20.324208"
    ],
    "values": [
      0.0,
      0.0,
      0.0,
      0.0,
      0.0,
      0.0
    ]
  },
  "CUGAL_FW_020.sim.size": {
    "steps": [
      0,
      1,
      2,
      3,
      4,
      5
    ],
    "timestamps": [
      "2024-06-03T20:38:22.747179",
      "2024-06-03T20:38:33.789672",
      "2024-06-03T20:38:45.052131",
      "2024-06-03T20:38:56.457930",
      "2024-06-03T20:39:08.747101",
      "2024-06-03T20:39:20.324098"
    ],
    "values": [
      143641,
      143641,
      143641,
      143641,
      143641,
      143641
    ]
  },
  "CUGAL_HUNGARIAN_MORE_GREEDY_FW_10.sim.max": {
    "steps": [
      0,
      1,
      2,
      3,
      4,
      5
    ],
    "timestamps": [
      "2024-06-03T20:38:23.648654",
      "2024-06-03T20:38:34.945554",
      "2024-06-03T20:38:45.947339",
      "2024-06-03T20:38:57.763312",
      "2024-06-03T20:39:10.002711",
      "2024-06-03T20:39:21.369995"
    ],
    "values": [
      1.0,
      1.0,
      1.0,
      1.0,
      1.0,
      1.0
    ]
  },
  "CUGAL_HUNGARIAN_MORE_GREEDY_FW_10.sim.min": {
    "steps": [
      0,
      1,
      2,
      3,
      4,
      5
    ],
    "timestamps": [
      "2024-06-03T20:38:23.648708",
      "2024-06-03T20:38:34.945602",
      "2024-06-03T20:38:45.947401",
      "2024-06-03T20:38:57.763373",
      "2024-06-03T20:39:10.002766",
      "2024-06-03T20:39:21.370053"
    ],
    "values": [
      0.0,
      0.0,
      0.0,
      0.0,
      0.0,
      0.0
    ]
  },
  "CUGAL_HUNGARIAN_MORE_GREEDY_FW_10.sim.size": {
    "steps": [
      0,
      1,
      2,
      3,
      4,
      5
    ],
    "timestamps": [
      "2024-06-03T20:38:23.648576",
      "2024-06-03T20:38:34.945476",
      "2024-06-03T20:38:45.947276",
      "2024-06-03T20:38:57.763243",
      "2024-06-03T20:39:10.002635",
      "2024-06-03T20:39:21.369933"
    ],
    "values": [
      143641,
      143641,
      143641,
      143641,
      143641,
      143641
    ]
  },
  "CUGAL_HUNGARIAN_MORE_GREEDY_FW_20.sim.max": {
    "steps": [
      0,
      1,
      2,
      3,
      4,
      5
    ],
    "timestamps": [
      "2024-06-03T20:38:24.170243",
      "2024-06-03T20:38:35.743885",
      "2024-06-03T20:38:46.442499",
      "2024-06-03T20:38:58.510087",
      "2024-06-03T20:39:10.870250",
      "2024-06-03T20:39:22.013173"
    ],
    "values": [
      1.0,
      1.0,
      1.0,
      1.0,
      1.0,
      1.0
    ]
  },
  "CUGAL_HUNGARIAN_MORE_GREEDY_FW_20.sim.min": {
    "steps": [
      0,
      1,
      2,
      3,
      4,
      5
    ],
    "timestamps": [
      "2024-06-03T20:38:24.170291",
      "2024-06-03T20:38:35.743941",
      "2024-06-03T20:38:46.442547",
      "2024-06-03T20:38:58.510136",
      "2024-06-03T20:39:10.870297",
      "2024-06-03T20:39:22.013219"
    ],
    "values": [
      0.0,
      0.0,
      0.0,
      0.0,
      0.0,
      0.0
    ]
  },
  "CUGAL_HUNGARIAN_MORE_GREEDY_FW_20.sim.size": {
    "steps": [
      0,
      1,
      2,
      3,
      4,
      5
    ],
    "timestamps": [
      "2024-06-03T20:38:24.170162",
      "2024-06-03T20:38:35.743810",
      "2024-06-03T20:38:46.442437",
      "2024-06-03T20:38:58.510020",
      "2024-06-03T20:39:10.870174",
      "2024-06-03T20:39:22.013108"
    ],
    "values": [
      143641,
      143641,
      143641,
      143641,
      143641,
      143641
    ]
  },
  "CUGAL_HUNGARIAN_MORE_GREEDy.sim.max": {
    "steps": [
      0,
      1,
      2,
      3,
      4,
      5
    ],
    "timestamps": [
      "2024-06-03T20:38:23.058001",
      "2024-06-03T20:38:34.148846",
      "2024-06-03T20:38:45.343152",
      "2024-06-03T20:38:56.809920",
      "2024-06-03T20:39:09.067418",
      "2024-06-03T20:39:20.654015"
    ],
    "values": [
      1.0,
      1.0,
      1.0,
      1.0,
      1.0,
      1.0
    ]
  },
  "CUGAL_HUNGARIAN_MORE_GREEDy.sim.min": {
    "steps": [
      0,
      1,
      2,
      3,
      4,
      5
    ],
    "timestamps": [
      "2024-06-03T20:38:23.058063",
      "2024-06-03T20:38:34.148891",
      "2024-06-03T20:38:45.343214",
      "2024-06-03T20:38:56.809970",
      "2024-06-03T20:39:09.067468",
      "2024-06-03T20:39:20.654060"
    ],
    "values": [
      0.0,
      0.0,
      0.0,
      0.0,
      0.0,
      0.0
    ]
  },
  "CUGAL_HUNGARIAN_MORE_GREEDy.sim.size": {
    "steps": [
      0,
      1,
      2,
      3,
      4,
      5
    ],
    "timestamps": [
      "2024-06-03T20:38:23.057888",
      "2024-06-03T20:38:34.148781",
      "2024-06-03T20:38:45.343090",
      "2024-06-03T20:38:56.809848",
      "2024-06-03T20:39:09.067332",
      "2024-06-03T20:39:20.653941"
    ],
    "values": [
      143641,
      143641,
      143641,
      143641,
      143641,
      143641
    ]
  },
  "CUGAL_LOG_FW_010.sim.max": {
    "steps": [
      0,
      1,
      2,
      3,
      4,
      5
    ],
    "timestamps": [
      "2024-06-03T20:38:24.519923",
      "2024-06-03T20:38:36.258330",
      "2024-06-03T20:38:46.855876",
      "2024-06-03T20:38:59.056347",
      "2024-06-03T20:39:11.344737",
      "2024-06-03T20:39:22.484699"
    ],
    "values": [
      1.0,
      1.0,
      1.0,
      1.0,
      1.0,
      1.0
    ]
  },
  "CUGAL_LOG_FW_010.sim.min": {
    "steps": [
      0,
      1,
      2,
      3,
      4,
      5
    ],
    "timestamps": [
      "2024-06-03T20:38:24.519982",
      "2024-06-03T20:38:36.258379",
      "2024-06-03T20:38:46.855942",
      "2024-06-03T20:38:59.056396",
      "2024-06-03T20:39:11.344783",
      "2024-06-03T20:39:22.484746"
    ],
    "values": [
      0.0,
      0.0,
      0.0,
      0.0,
      0.0,
      0.0
    ]
  },
  "CUGAL_LOG_FW_010.sim.size": {
    "steps": [
      0,
      1,
      2,
      3,
      4,
      5
    ],
    "timestamps": [
      "2024-06-03T20:38:24.519855",
      "2024-06-03T20:38:36.258260",
      "2024-06-03T20:38:46.855813",
      "2024-06-03T20:38:59.056278",
      "2024-06-03T20:39:11.344671",
      "2024-06-03T20:39:22.484636"
    ],
    "values": [
      143641,
      143641,
      143641,
      143641,
      143641,
      143641
    ]
  },
  "CUGAL_LOG_FW_020.sim.max": {
    "steps": [
      0,
      1,
      2,
      3,
      4,
      5
    ],
    "timestamps": [
      "2024-06-03T20:38:24.714554",
      "2024-06-03T20:38:36.434567",
      "2024-06-03T20:38:46.974034",
      "2024-06-03T20:38:59.181284",
      "2024-06-03T20:39:11.499045",
      "2024-06-03T20:39:22.627759"
    ],
    "values": [
      1.0,
      1.0,
      1.0,
      1.0,
      1.0,
      1.0
    ]
  },
  "CUGAL_LOG_FW_020.sim.min": {
    "steps": [
      0,
      1,
      2,
      3,
      4,
      5
    ],
    "timestamps": [
      "2024-06-03T20:38:24.714612",
      "2024-06-03T20:38:36.434616",
      "2024-06-03T20:38:46.974081",
      "2024-06-03T20:38:59.181334",
      "2024-06-03T20:39:11.499093",
      "2024-06-03T20:39:22.627815"
    ],
    "values": [
      0.0,
      0.0,
      0.0,
      0.0,
      0.0,
      0.0
    ]
  },
  "CUGAL_LOG_FW_020.sim.size": {
    "steps": [
      0,
      1,
      2,
      3,
      4,
      5
    ],
    "timestamps": [
      "2024-06-03T20:38:24.714469",
      "2024-06-03T20:38:36.434506",
      "2024-06-03T20:38:46.973972",
      "2024-06-03T20:38:59.181206",
      "2024-06-03T20:39:11.498974",
      "2024-06-03T20:39:22.627693"
    ],
    "values": [
      143641,
      143641,
      143641,
      143641,
      143641,
      143641
    ]
  },
  "CUGAL_LOG_HUNGARIAN_MORE_GREEDY.sim.max": {
    "steps": [
      0,
      1,
      2,
      3,
      4,
      5
    ],
    "timestamps": [
      "2024-06-03T20:38:24.990538",
      "2024-06-03T20:38:36.787164",
      "2024-06-03T20:38:47.265222",
      "2024-06-03T20:38:59.533846",
      "2024-06-03T20:39:11.818930",
      "2024-06-03T20:39:22.958375"
    ],
    "values": [
      1.0,
      1.0,
      1.0,
      1.0,
      1.0,
      1.0
    ]
  },
  "CUGAL_LOG_HUNGARIAN_MORE_GREEDY.sim.min": {
    "steps": [
      0,
      1,
      2,
      3,
      4,
      5
    ],
    "timestamps": [
      "2024-06-03T20:38:24.990596",
      "2024-06-03T20:38:36.787211",
      "2024-06-03T20:38:47.265272",
      "2024-06-03T20:38:59.533893",
      "2024-06-03T20:39:11.818983",
      "2024-06-03T20:39:22.958435"
    ],
    "values": [
      0.0,
      0.0,
      0.0,
      0.0,
      0.0,
      0.0
    ]
  },
  "CUGAL_LOG_HUNGARIAN_MORE_GREEDY.sim.size": {
    "steps": [
      0,
      1,
      2,
      3,
      4,
      5
    ],
    "timestamps": [
      "2024-06-03T20:38:24.990445",
      "2024-06-03T20:38:36.787104",
      "2024-06-03T20:38:47.265145",
      "2024-06-03T20:38:59.533779",
      "2024-06-03T20:39:11.818858",
      "2024-06-03T20:39:22.958310"
    ],
    "values": [
      143641,
      143641,
      143641,
      143641,
      143641,
      143641
    ]
  },
  "CUGAL_LOG_HUNGARIAN_MORE_GREEDY_FW_10.sim.max": {
    "steps": [
      0,
      1,
      2,
      3,
      4,
      5
    ],
    "timestamps": [
      "2024-06-03T20:38:25.119816",
      "2024-06-03T20:38:37.005048",
      "2024-06-03T20:38:47.443189",
      "2024-06-03T20:38:59.779707",
      "2024-06-03T20:39:12.030413",
      "2024-06-03T20:39:23.162293"
    ],
    "values": [
      1.0,
      1.0,
      1.0,
      1.0,
      1.0,
      1.0
    ]
  },
  "CUGAL_LOG_HUNGARIAN_MORE_GREEDY_FW_10.sim.min": {
    "steps": [
      0,
      1,
      2,
      3,
      4,
      5
    ],
    "timestamps": [
      "2024-06-03T20:38:25.119879",
      "2024-06-03T20:38:37.005093",
      "2024-06-03T20:38:47.443244",
      "2024-06-03T20:38:59.779755",
      "2024-06-03T20:39:12.030460",
      "2024-06-03T20:39:23.162340"
    ],
    "values": [
      0.0,
      0.0,
      0.0,
      0.0,
      0.0,
      0.0
    ]
  },
  "CUGAL_LOG_HUNGARIAN_MORE_GREEDY_FW_10.sim.size": {
    "steps": [
      0,
      1,
      2,
      3,
      4,
      5
    ],
    "timestamps": [
      "2024-06-03T20:38:25.119743",
      "2024-06-03T20:38:37.004983",
      "2024-06-03T20:38:47.443131",
      "2024-06-03T20:38:59.779641",
      "2024-06-03T20:39:12.030342",
      "2024-06-03T20:39:23.162224"
    ],
    "values": [
      143641,
      143641,
      143641,
      143641,
      143641,
      143641
    ]
  },
  "CUGAL_LOG_HUNGARIAN_MORE_GREEDY_FW_20.sim.max": {
    "steps": [
      0,
      1,
      2,
      3,
      4,
      5
    ],
    "timestamps": [
      "2024-06-03T20:38:25.232572",
      "2024-06-03T20:38:37.208098",
      "2024-06-03T20:38:47.591076",
      "2024-06-03T20:38:59.932265",
      "2024-06-03T20:39:12.211954",
      "2024-06-03T20:39:23.334312"
    ],
    "values": [
      1.0,
      1.0,
      1.0,
      1.0,
      1.0,
      1.0
    ]
  },
  "CUGAL_LOG_HUNGARIAN_MORE_GREEDY_FW_20.sim.min": {
    "steps": [
      0,
      1,
      2,
      3,
      4,
      5
    ],
    "timestamps": [
      "2024-06-03T20:38:25.232622",
      "2024-06-03T20:38:37.208143",
      "2024-06-03T20:38:47.591121",
      "2024-06-03T20:38:59.932312",
      "2024-06-03T20:39:12.212010",
      "2024-06-03T20:39:23.334359"
    ],
    "values": [
      0.0,
      0.0,
      0.0,
      0.0,
      0.0,
      0.0
    ]
  },
  "CUGAL_LOG_HUNGARIAN_MORE_GREEDY_FW_20.sim.size": {
    "steps": [
      0,
      1,
      2,
      3,
      4,
      5
    ],
    "timestamps": [
      "2024-06-03T20:38:25.232500",
      "2024-06-03T20:38:37.208042",
      "2024-06-03T20:38:47.591019",
      "2024-06-03T20:38:59.932202",
      "2024-06-03T20:39:12.211885",
      "2024-06-03T20:39:23.334243"
    ],
    "values": [
      143641,
      143641,
      143641,
      143641,
      143641,
      143641
    ]
  },
  "CUGAL_Sparse_LOG.sim.max": {
    "steps": [
      0,
      1,
      2,
      3,
      4,
      5
    ],
    "timestamps": [
      "2024-06-03T20:38:24.417581",
      "2024-06-03T20:38:36.069348",
      "2024-06-03T20:38:46.705084",
      "2024-06-03T20:38:58.833816",
      "2024-06-03T20:39:11.161669",
      "2024-06-03T20:39:22.307864"
    ],
    "values": [
      1.0,
      1.0,
      1.0,
      1.0,
      1.0,
      1.0
    ]
  },
  "CUGAL_Sparse_LOG.sim.min": {
    "steps": [
      0,
      1,
      2,
      3,
      4,
      5
    ],
    "timestamps": [
      "2024-06-03T20:38:24.417633",
      "2024-06-03T20:38:36.069394",
      "2024-06-03T20:38:46.705134",
      "2024-06-03T20:38:58.833866",
      "2024-06-03T20:39:11.161729",
      "2024-06-03T20:39:22.307912"
    ],
    "values": [
      0.0,
      0.0,
      0.0,
      0.0,
      0.0,
      0.0
    ]
  },
  "CUGAL_Sparse_LOG.sim.size": {
    "steps": [
      0,
      1,
      2,
      3,
      4,
      5
    ],
    "timestamps": [
      "2024-06-03T20:38:24.417508",
      "2024-06-03T20:38:36.069283",
      "2024-06-03T20:38:46.705019",
      "2024-06-03T20:38:58.833746",
      "2024-06-03T20:39:11.161594",
      "2024-06-03T20:39:22.307800"
    ],
    "values": [
      143641,
      143641,
      143641,
      143641,
      143641,
      143641
    ]
  },
  "CUGAL_Sparse_MIX.sim.max": {
    "steps": [
      0,
      1,
      2,
      3,
      4,
      5
    ],
    "timestamps": [
      "2024-06-03T20:38:21.695326",
      "2024-06-03T20:38:32.246783",
      "2024-06-03T20:38:43.992808",
      "2024-06-03T20:38:54.807812",
      "2024-06-03T20:39:06.998797",
      "2024-06-03T20:39:19.019214"
    ],
    "values": [
      1.0,
      1.0,
      1.0,
      1.0,
      1.0,
      1.0
    ]
  },
  "CUGAL_Sparse_MIX.sim.min": {
    "steps": [
      0,
      1,
      2,
      3,
      4,
      5
    ],
    "timestamps": [
      "2024-06-03T20:38:21.695385",
      "2024-06-03T20:38:32.246838",
      "2024-06-03T20:38:43.992860",
      "2024-06-03T20:38:54.807874",
      "2024-06-03T20:39:06.998857",
      "2024-06-03T20:39:19.019271"
    ],
    "values": [
      0.0,
      0.0,
      0.0,
      0.0,
      0.0,
      0.0
    ]
  },
  "CUGAL_Sparse_MIX.sim.size": {
    "steps": [
      0,
      1,
      2,
      3,
      4,
      5
    ],
    "timestamps": [
      "2024-06-03T20:38:21.695231",
      "2024-06-03T20:38:32.246689",
      "2024-06-03T20:38:43.992718",
      "2024-06-03T20:38:54.807725",
      "2024-06-03T20:39:06.998681",
      "2024-06-03T20:39:19.019141"
    ],
    "values": [
      143641,
      143641,
      143641,
      143641,
      143641,
      143641
    ]
  },
  "graph.Source.disc": {
    "steps": [
      0,
      1,
      2,
      3,
      4,
      5
    ],
    "timestamps": [
      "2024-06-03T20:38:14.098105",
      "2024-06-03T20:38:25.236647",
      "2024-06-03T20:38:37.211693",
      "2024-06-03T20:38:47.595097",
      "2024-06-03T20:38:59.936324",
      "2024-06-03T20:39:12.215467"
    ],
    "values": [
      false,
      false,
      false,
      false,
      false,
      false
    ]
  },
  "graph.Source.e": {
    "steps": [
      0,
      1,
      2,
      3,
      4,
      5
    ],
    "timestamps": [
      "2024-06-03T20:38:14.098131",
      "2024-06-03T20:38:25.236655",
      "2024-06-03T20:38:37.211701",
      "2024-06-03T20:38:47.595105",
      "2024-06-03T20:38:59.936331",
      "2024-06-03T20:39:12.215475"
    ],
    "values": [
      914,
      914,
      914,
      914,
      914,
      914
    ]
  },
  "graph.Source.n": {
    "steps": [
      0,
      1,
      2,
      3,
      4,
      5
    ],
    "timestamps": [
      "2024-06-03T20:38:14.098126",
      "2024-06-03T20:38:25.236652",
      "2024-06-03T20:38:37.211699",
      "2024-06-03T20:38:47.595103",
      "2024-06-03T20:38:59.936329",
      "2024-06-03T20:39:12.215472"
    ],
    "values": [
      379,
      379,
      379,
      379,
      379,
      379
    ]
  },
  "graph.Target.disc": {
    "steps": [
      0,
      1,
      2,
      3,
      4,
      5
    ],
    "timestamps": [
      "2024-06-03T20:38:14.098134",
      "2024-06-03T20:38:25.236656",
      "2024-06-03T20:38:37.211745",
      "2024-06-03T20:38:47.595152",
      "2024-06-03T20:38:59.936385",
      "2024-06-03T20:39:12.215512"
    ],
    "values": [
      false,
      false,
      true,
      true,
      true,
      true
    ]
  },
  "graph.Target.e": {
    "steps": [
      0,
      1,
      2,
      3,
      4,
      5
    ],
    "timestamps": [
      "2024-06-03T20:38:14.098142",
      "2024-06-03T20:38:25.236659",
      "2024-06-03T20:38:37.211748",
      "2024-06-03T20:38:47.595157",
      "2024-06-03T20:38:59.936388",
      "2024-06-03T20:39:12.215515"
    ],
    "values": [
      914,
      864,
      839,
      776,
      744,
      694
    ]
  },
  "graph.Target.n": {
    "steps": [
      0,
      1,
      2,
      3,
      4,
      5
    ],
    "timestamps": [
      "2024-06-03T20:38:14.098139",
      "2024-06-03T20:38:25.236657",
      "2024-06-03T20:38:37.211747",
      "2024-06-03T20:38:47.595154",
      "2024-06-03T20:38:59.936387",
      "2024-06-03T20:39:12.215514"
    ],
    "values": [
      379,
      379,
      379,
      379,
      379,
      379
    ]
  }
}