{
  "CUGAL_Sparse_LOG.sim.max": {
    "steps": [
      0,
      1,
      2,
      3,
      4
    ],
    "timestamps": [
      "2024-04-30T07:18:04.877962",
      "2024-04-30T07:18:57.262338",
      "2024-04-30T07:19:50.060298",
      "2024-04-30T07:20:42.822963",
      "2024-04-30T07:21:35.905742"
    ],
    "values": [
      1.0,
      1.0,
      1.0,
      1.0,
      1.0
    ]
  },
  "CUGAL_Sparse_LOG.sim.min": {
    "steps": [
      0,
      1,
      2,
      3,
      4
    ],
    "timestamps": [
      "2024-04-30T07:18:04.878471",
      "2024-04-30T07:18:57.262850",
      "2024-04-30T07:19:50.060875",
      "2024-04-30T07:20:42.823514",
      "2024-04-30T07:21:35.906347"
    ],
    "values": [
      0.0,
      0.0,
      0.0,
      0.0,
      0.0
    ]
  },
  "CUGAL_Sparse_LOG.sim.size": {
    "steps": [
      0,
      1,
      2,
      3,
      4
    ],
    "timestamps": [
      "2024-04-30T07:18:04.877362",
      "2024-04-30T07:18:57.261750",
      "2024-04-30T07:19:50.059663",
      "2024-04-30T07:20:42.822357",
      "2024-04-30T07:21:35.905076"
    ],
    "values": [
      1008016,
      1008016,
      1008016,
      1008016,
      1008016
    ]
  },
  "CUGAL_Sparse_MIX.sim.max": {
    "steps": [
      0,
      1,
      2,
      3,
      4
    ],
    "timestamps": [
      "2024-04-30T07:18:09.308777",
      "2024-04-30T07:19:02.414092",
      "2024-04-30T07:19:55.222279",
      "2024-04-30T07:20:47.991063",
      "2024-04-30T07:21:41.097677"
    ],
    "values": [
      1.0,
      1.0,
      1.0,
      1.0,
      1.0
    ]
  },
  "CUGAL_Sparse_MIX.sim.min": {
    "steps": [
      0,
      1,
      2,
      3,
      4
    ],
    "timestamps": [
      "2024-04-30T07:18:09.309012",
      "2024-04-30T07:19:02.414636",
      "2024-04-30T07:19:55.222815",
      "2024-04-30T07:20:47.991595",
      "2024-04-30T07:21:41.098183"
    ],
    "values": [
      0.0,
      0.0,
      0.0,
      0.0,
      0.0
    ]
  },
  "CUGAL_Sparse_MIX.sim.size": {
    "steps": [
      0,
      1,
      2,
      3,
      4
    ],
    "timestamps": [
      "2024-04-30T07:18:09.307896",
      "2024-04-30T07:19:02.413463",
      "2024-04-30T07:19:55.221671",
      "2024-04-30T07:20:47.990459",
      "2024-04-30T07:21:41.097096"
    ],
    "values": [
      1008016,
      1008016,
      1008016,
      1008016,
      1008016
    ]
  },
  "FUGAL.sim.max": {
    "steps": [
      0,
      1,
      2,
      3,
      4
    ],
    "timestamps": [
      "2024-04-30T07:18:03.193807",
      "2024-04-30T07:18:53.917063",
      "2024-04-30T07:19:46.692044",
      "2024-04-30T07:20:39.457757",
      "2024-04-30T07:21:32.487503"
    ],
    "values": [
      1.0,
      1.0,
      1.0,
      1.0,
      1.0
    ]
  },
  "FUGAL.sim.min": {
    "steps": [
      0,
      1,
      2,
      3,
      4
    ],
    "timestamps": [
      "2024-04-30T07:18:03.194308",
      "2024-04-30T07:18:53.917590",
      "2024-04-30T07:19:46.692564",
      "2024-04-30T07:20:39.458227",
      "2024-04-30T07:21:32.488019"
    ],
    "values": [
      0.0,
      0.0,
      0.0,
      0.0,
      0.0
    ]
  },
  "FUGAL.sim.size": {
    "steps": [
      0,
      1,
      2,
      3,
      4
    ],
    "timestamps": [
      "2024-04-30T07:18:03.189757",
      "2024-04-30T07:18:53.916456",
      "2024-04-30T07:19:46.691450",
      "2024-04-30T07:20:39.457235",
      "2024-04-30T07:21:32.486951"
    ],
    "values": [
      1008016,
      1008016,
      1008016,
      1008016,
      1008016
    ]
  },
  "graph.Source.disc": {
    "steps": [
      0,
      1,
      2,
      3,
      4
    ],
    "timestamps": [
      "2024-04-30T07:17:19.072999",
      "2024-04-30T07:18:09.408978",
      "2024-04-30T07:19:02.514059",
      "2024-04-30T07:19:55.323370",
      "2024-04-30T07:20:48.090388"
    ],
    "values": [
      false,
      false,
      false,
      false,
      false
    ]
  },
  "graph.Source.e": {
    "steps": [
      0,
      1,
      2,
      3,
      4
    ],
    "timestamps": [
      "2024-04-30T07:17:19.073023",
      "2024-04-30T07:18:09.408991",
      "2024-04-30T07:19:02.514072",
      "2024-04-30T07:19:55.323386",
      "2024-04-30T07:20:48.090401"
    ],
    "values": [
      8323,
      8323,
      8323,
      8323,
      8323
    ]
  },
  "graph.Source.n": {
    "steps": [
      0,
      1,
      2,
      3,
      4
    ],
    "timestamps": [
      "2024-04-30T07:17:19.073019",
      "2024-04-30T07:18:09.408989",
      "2024-04-30T07:19:02.514069",
      "2024-04-30T07:19:55.323383",
      "2024-04-30T07:20:48.090399"
    ],
    "values": [
      1004,
      1004,
      1004,
      1004,
      1004
    ]
  },
  "graph.Target.disc": {
    "steps": [
      0,
      1,
      2,
      3,
      4
    ],
    "timestamps": [
      "2024-04-30T07:17:19.073025",
      "2024-04-30T07:18:09.408993",
      "2024-04-30T07:19:02.514075",
      "2024-04-30T07:19:55.323387",
      "2024-04-30T07:20:48.090403"
    ],
    "values": [
      false,
      false,
      false,
      false,
      false
    ]
  },
  "graph.Target.e": {
    "steps": [
      0,
      1,
      2,
      3,
      4
    ],
    "timestamps": [
      "2024-04-30T07:17:19.073030",
      "2024-04-30T07:18:09.408996",
      "2024-04-30T07:19:02.514079",
      "2024-04-30T07:19:55.323390",
      "2024-04-30T07:20:48.090406"
    ],
    "values": [
      8739,
      9155,
      9571,
      9987,
      10403
    ]
  },
  "graph.Target.n": {
    "steps": [
      0,
      1,
      2,
      3,
      4
    ],
    "timestamps": [
      "2024-04-30T07:17:19.073028",
      "2024-04-30T07:18:09.408995",
      "2024-04-30T07:19:02.514077",
      "2024-04-30T07:19:55.323389",
      "2024-04-30T07:20:48.090405"
    ],
    "values": [
      1004,
      1004,
      1004,
      1004,
      1004
    ]
  }
}